lab_sum/sum_res_carry/bcd7seg_hex.v
/*
 * Generated by Digital. Don't modify this file!
 * Any changes will be lost if this file is regenerated.
 */

module bcd7seg_hex (
	input s3, s2, s1, s0, c0,
	output a, b, c, d, e, f, g, h
	);
	wire s4;
	wire s5;
	wire s6;
	wire s7;
	assign h = ~c0;
	assign s6 = ~ s3;
	assign s5 = ~ s2;
	assign s4 = ~ s1;
	assign s7 = ~ s0;
	assign a = ((s0 & s4 & s5 & s6) | (s7 & s4 & s2) | (s0 & s1 & s5 & s3) | (s4 & s2 & s3));
	assign b = ((s0 & s4 & s2 & s6) | (s7 & s1 & s2) | (s0 & s1 & s3) | (s7 & s2 & s3));
	assign c = ((s7 & s1 & s5 & s6) | (s7 & s2 & s3) | (s1 & s2 & s3));
	assign d = ((s0 & s4 & s5 & s6) | (s7 & s4 & s2 & s6) | (s0 & s1 & s2) | (s7 & s1 & s5 & s3));
	assign e = ((s0 & s6) | (s0 & s4 & s5) | (s4 & s2 & s6));
	assign f = ((s0 & s5 & s6) | (s0 & s1 & s6) | (s1 & s5 & s6) | (s4 & s2 & s3));
	assign g = ((s0 & s1 & s2 & s6) | (s4 & s5 & s6));
endmodule

lab_sum/sum_res_carry/sumres.v

module sumres(
  input a,b,c_in,op,
  output s,c_out
);
  assign s = ((a ^ b) ^ c_in);
  assign c_out = (((a ^ op) & b) | (((a ^ op) | b) & c_in));
endmodule

lab_sum/sum_res_carry/full_sumres.v
module full_sumres (
	input in_b0, in_b1, in_b2, in_b3, in_a0, in_a1, in_a2, in_a3, in_cy, ope,
	output out_s0, out_s1, out_s2, out_s3, out_cy0
	);
	wire f_out_cy0_f_in_cy1;
	wire f_out_cy1_f_in_cy2;
	wire f_out_cy2_f_in_cy3;

	sumres sumres0(in_b0,in_a0,in_cy,op,f_out_cy0_f_in_cy1,out_s0);
	sumres sumres1(in_b1,in_a1,f_out_cy0_f_in_cy1,op,f_out_cy1_f_in_cy2,out_s1);
	sumres sumres2(in_b2,in_a2,f_out_cy1_f_in_cy2,op,f_out_cy2_f_in_cy3,out_s2);
	sumres sumres3(in_b3,in_a3,f_out_cy2_f_in_cy3,op,out_cy0,out_s3);

endmodule

lab_sum/sum_res_carry/sumres7seg_hex.v
module sumres7seg_hex (
	input x0,x1,x2,x3,y0,y1,y2,y3,carry_in,op,
	output led_a,led_b,led_c,led_d,led_e,led_f,led_g,led_h);

	wire first;
	wire second;
	wire third;
	wire fourth;
	wire fifth;
	full_sumres full_sumres0(x0,x1,x2,x3,y0,y1,y2,y3,carry_in,op,first,second,third,fourth,fifth);
	bcd7seg_hex deco(fourth,third,second,first,fifth,led_a,led_b,led_c,led_d,led_e,led_f,led_g,led_h);
endmodule

lab_sum/sum_res_carry/sumres7seg_hex_tb.v
// `timescale 10ns/10ns // <time_unit>/<time_precision
module testbech;

  // // Determinar el tamaño de los wire como de los estímulos
  parameter INPUT_SIZE = 10;
  parameter OUTPUT_SIZE = 8;

  // // STIMULUS 1
  // reg a = 0, b = 0;
  // initial
  // begin
  //    # 17 a = 1; b = 1;
  //    # 11 a = 1; b = 0;
  //    # 29 a = 1; b = 1;
  //    # 11 a = 1; b = 0;
  //    # 100 $finish(); // [stop(), $finish()]
  // end

  // // STIMULUS 2
   reg [INPUT_SIZE-1:0] inputs;
  // inputs[2] inputs[1] inputs[1]
   integer i;
   initial
   begin
     inputs = 0;
     for (i=0; i<2**INPUT_SIZE; i=i+1) // 2 elevado a la INPUT_SIZE , en el ejemplo 2^3 = 8 combinaciones
     begin
       inputs = i;
       #1;
     end
   end

  // // STIMULUS ARGS
  // initial
  // begin
  //   if(! $value$plusargs("inputs=%b", inputs)) begin
  //     $display("ERROR: please specify +inputs=<value> to start.");
  //     $finish;
  //   end

  //   wait (outs) $display("outs = %d", outs);
  //   #1
  //   $finish;
  // end

  // // CLOCK STIMULUS
  // Make a regular pulsing clock.
  // reg clk = 0;
  // always #5 clk = !clk;

  // initial
  // begin
  //   #2E9 $finish(); // [stop(), $finish()]
  // end

  // // RESULT FOR DEVICE/DESIGN UNDER TEST
  wire [OUTPUT_SIZE-1:0]value;

  // // DEVICE/DESIGN UNDER TEST
  sumres7seg_hex dut(inputs[0],inputs [1],inputs[2],inputs [3],inputs[4],inputs [5],inputs[6],inputs [7],inputs[8],inputs [9],
  (value[7]),(value[6]),(value[5]),(value[4]),(value[3]),(value[2]),(value[1]),(value[0]));

  // // MONITOR
  // initial
    // $monitor("Time: %t, a = %d, b = %d => out = %d",
    //   $time, a, b, value);

  // // WAVES IN VCD TO OPEN IN GTKWAVE
  initial
  begin
    $dumpfile("top.vcd");
    $dumpvars(0, testbech);
  end
endmodule

lab_sum/sum_res_carry/sim/top.vcd
$date
	Mon Oct 16 18:59:02 2023
$end
$version
	Icarus Verilog
$end
$timescale
	1s
$end
$scope module testbech $end
$var wire 8 ! value [7:0] $end
$var parameter 32 " INPUT_SIZE $end
$var parameter 32 # OUTPUT_SIZE $end
$var reg 10 $ inputs [9:0] $end
$var integer 32 % i [31:0] $end
$scope module dut $end
$var wire 1 & carry_in $end
$var wire 1 ' op $end
$var wire 1 ( x0 $end
$var wire 1 ) x1 $end
$var wire 1 * x2 $end
$var wire 1 + x3 $end
$var wire 1 , y0 $end
$var wire 1 - y1 $end
$var wire 1 . y2 $end
$var wire 1 / y3 $end
$var wire 1 0 third $end
$var wire 1 1 second $end
$var wire 1 2 led_h $end
$var wire 1 3 led_g $end
$var wire 1 4 led_f $end
$var wire 1 5 led_e $end
$var wire 1 6 led_d $end
$var wire 1 7 led_c $end
$var wire 1 8 led_b $end
$var wire 1 9 led_a $end
$var wire 1 : fourth $end
$var wire 1 ; first $end
$var wire 1 < fifth $end
$scope module deco $end
$var wire 1 9 a $end
$var wire 1 8 b $end
$var wire 1 7 c $end
$var wire 1 6 d $end
$var wire 1 5 e $end
$var wire 1 4 f $end
$var wire 1 3 g $end
$var wire 1 2 h $end
$var wire 1 = s4 $end
$var wire 1 > s5 $end
$var wire 1 ? s6 $end
$var wire 1 @ s7 $end
$var wire 1 : s3 $end
$var wire 1 0 s2 $end
$var wire 1 1 s1 $end
$var wire 1 ; s0 $end
$var wire 1 < c0 $end
$upscope $end
$scope module full_sumres0 $end
$var wire 1 , in_a0 $end
$var wire 1 - in_a1 $end
$var wire 1 . in_a2 $end
$var wire 1 / in_a3 $end
$var wire 1 ( in_b0 $end
$var wire 1 ) in_b1 $end
$var wire 1 * in_b2 $end
$var wire 1 + in_b3 $end
$var wire 1 & in_cy $end
$var wire 1 A op $end
$var wire 1 ' ope $end
$var wire 1 : out_s3 $end
$var wire 1 0 out_s2 $end
$var wire 1 1 out_s1 $end
$var wire 1 ; out_s0 $end
$var wire 1 < out_cy0 $end
$var wire 1 B f_out_cy2_f_in_cy3 $end
$var wire 1 C f_out_cy1_f_in_cy2 $end
$var wire 1 D f_out_cy0_f_in_cy1 $end
$scope module sumres0 $end
$var wire 1 ( a $end
$var wire 1 , b $end
$var wire 1 & c_in $end
$var wire 1 ; c_out $end
$var wire 1 A op $end
$var wire 1 D s $end
$upscope $end
$scope module sumres1 $end
$var wire 1 ) a $end
$var wire 1 - b $end
$var wire 1 D c_in $end
$var wire 1 1 c_out $end
$var wire 1 A op $end
$var wire 1 C s $end
$upscope $end
$scope module sumres2 $end
$var wire 1 * a $end
$var wire 1 . b $end
$var wire 1 C c_in $end
$var wire 1 0 c_out $end
$var wire 1 A op $end
$var wire 1 B s $end
$upscope $end
$scope module sumres3 $end
$var wire 1 + a $end
$var wire 1 / b $end
$var wire 1 B c_in $end
$var wire 1 : c_out $end
$var wire 1 A op $end
$var wire 1 < s $end
$upscope $end
$upscope $end
$upscope $end
$upscope $end
$enddefinitions $end
$comment Show the parameter values. $end
$dumpall
b1000 #
b1010 "
$end
#0
$dumpvars
0D
0C
0B
zA
1@
1?
1>
1=
0<
0;
0:
09
08
07
06
05
04
13
12
01
00
0/
0.
0-
0,
0+
0*
0)
0(
0'
0&
b0 %
b0 $
b11 !
$end
#1
x7
x8
x6
x9
x5
x4
x3
x?
bx0 !
02
x:
x>
1<
x0
x=
1B
x1
1C
1D
1(
b1 $
b1 %
#2
x6
x3
x5
x7
x8
x9
x?
1=
bx0 !
02
x:
x>
01
1<
x0
1B
0D
1C
0(
1)
b10 $
b10 %
#3
06
09
08
05
1?
b0x00xx1 !
12
0:
1>
0<
00
x=
0B
x1
0C
1D
1(
b11 $
b11 %
#4
07
08
09
04
05
06
1=
1>
x?
01
00
b0x0 !
02
x:
1<
0D
0C
1B
0(
0)
1*
b100 $
b100 %
#5
x6
x9
x7
x8
x4
x5
1?
bx1 !
12
0:
x>
0<
x0
x=
0B
x1
1C
1D
1(
b101 $
b101 %
#6
x6
07
04
08
x9
x5
1?
1=
bx00xx0x1 !
12
0:
x>
01
0<
x0
0B
0D
1C
0(
1)
b110 $
b110 %
#7
09
x7
x4
05
x?
b0xx0xx0 !
02
x:
1>
1<
00
x=
1B
x1
0C
1D
1(
b111 $
b111 %
#8
07
13
04
08
09
05
06
1=
1>
1?
01
00
0:
b10 !
02
0D
0C
0B
1<
0(
0)
0*
1+
b1000 $
b1000 %
#9
x7
x8
x6
x9
x5
x4
x3
x?
bx1 !
12
x:
x>
0<
x0
x=
1B
x1
1C
1D
1(
b1001 $
b1001 %
#10
x6
x3
x5
x7
x8
x9
x?
1=
bx1 !
12
x:
x>
01
0<
x0
1B
0D
1C
0(
1)
b1010 $
b1010 %
#11
06
09
08
05
1?
b0x00xx0 !
02
0:
1>
1<
00
x=
0B
x1
0C
1D
1(
b1011 $
b1011 %
#12
07
08
09
04
05
06
1=
1>
x?
01
00
b0x1 !
12
x:
0<
0D
0C
1B
0(
0)
1*
b1100 $
b1100 %
#13
x6
x9
x7
x8
x4
x5
1?
bx0 !
02
0:
x>
1<
x0
x=
0B
x1
1C
1D
1(
b1101 $
b1101 %
#14
x6
07
04
08
x9
x5
1?
1=
bx00xx0x0 !
02
0:
x>
01
1<
x0
0B
0D
1C
0(
1)
b1110 $
b1110 %
#15
09
x7
x4
05
x?
b0xx0xx1 !
12
x:
1>
0<
00
x=
1B
x1
0C
1D
1(
b1111 $
b1111 %
#16
x9
x6
x8
x>
x?
x5
x0
x:
bx0 !
02
x@
1C
1B
1<
x;
0(
0)
0*
0+
1,
b10000 $
b10000 %
#17
08
13
07
1?
bx00xxx11 !
12
0:
1>
0<
00
1=
0B
01
0C
0D
1(
b10001 $
b10001 %
#18
x3
x7
08
1?
x=
bx0xxxxx1 !
12
0:
1>
x1
0<
00
0B
1D
0C
0(
1)
b10010 $
b10010 %
#19
x8
x3
x?
bx0 !
02
x:
x>
1<
x0
1=
1B
01
1C
0D
1(
b10011 $
b10011 %
#20
x7
x=
x>
1?
x1
x0
bx1 !
12
0:
0<
1D
1C
0B
0(
0)
1*
b10100 $
b10100 %
#21
08
07
x?
bx00xxxx0 !
02
x:
1>
1<
00
1=
1B
01
0C
0D
1(
b10101 $
b10101 %
#22
x8
x7
x?
x=
bx0 !
02
x:
1>
x1
1<
00
1B
1D
0C
0(
1)
b10110 $
b10110 %
#23
07
x8
1?
bx0xxxx1 !
12
0:
x>
0<
x0
1=
0B
01
1C
0D
1(
b10111 $
b10111 %
#24
x7
x=
x>
x?
x1
x0
x:
bx1 !
12
1D
1C
1B
0<
0(
0)
0*
1+
b11000 $
b11000 %
#25
08
13
07
1?
bx00xxx10 !
02
0:
1>
1<
00
1=
0B
01
0C
0D
1(
b11001 $
b11001 %
#26
x3
x7
08
1?
x=
bx0xxxxx0 !
02
0:
1>
x1
1<
00
0B
1D
0C
0(
1)
b11010 $
b11010 %
#27
x8
x3
x?
bx1 !
12
x:
x>
0<
x0
1=
1B
01
1C
0D
1(
b11011 $
b11011 %
#28
x7
x=
x>
1?
x1
x0
bx0 !
02
0:
1<
1D
1C
0B
0(
0)
1*
b11100 $
b11100 %
#29
08
07
x?
bx00xxxx1 !
12
x:
1>
0<
00
1=
1B
01
0C
0D
1(
b11101 $
b11101 %
#30
x8
x7
x?
x=
bx1 !
12
x:
1>
x1
0<
00
1B
1D
0C
0(
1)
b11110 $
b11110 %
#31
07
x8
1?
bx0xxxx0 !
02
0:
x>
1<
x0
1=
0B
01
1C
0D
1(
b11111 $
b11111 %
#32
x7
x?
x:
bx0 !
02
1@
x=
1B
1<
0;
x1
0(
0)
0*
0+
0,
1-
b100000 $
b100000 %
#33
06
14
09
17
08
05
03
1?
b100101 !
12
0:
1>
0<
00
0=
0B
11
0C
1D
1(
b100001 $
b100001 %
#34
x4
x3
06
x7
08
1?
x=
b0x00xx1 !
12
0:
1>
x1
0<
00
0B
0D
0C
0(
1)
b100010 $
b100010 %
#35
x7
x8
x4
x6
03
x?
b0xxx0x00 !
02
x:
x>
1<
x0
0=
1B
11
1C
1D
1(
b100011 $
b100011 %
#36
x9
x5
x8
x3
x6
x=
x>
1?
x1
x0
bx1 !
12
0:
0<
0D
1C
0B
0(
0)
1*
b100100 $
b100100 %
#37
09
08
05
03
x?
b0xx0x00 !
02
x:
1>
1<
00
0=
1B
11
0C
1D
1(
b100101 $
b100101 %
#38
08
x3
x6
x?
x=
b0xx0xx0 !
02
x:
1>
x1
1<
00
1B
0D
0C
0(
1)
b100110 $
b100110 %
#39
x8
06
03
1?
b0xx00x01 !
12
0:
x>
0<
x0
0=
0B
11
1C
1D
1(
b100111 $
b100111 %
#40
x9
x5
x3
x8
x6
x=
x>
x?
x1
x0
x:
bx1 !
12
0D
1C
1B
0<
0(
0)
0*
1+
b101000 $
b101000 %
#41
06
14
09
17
08
05
03
1?
b100100 !
02
0:
1>
1<
00
0=
0B
11
0C
1D
1(
b101001 $
b101001 %
#42
x4
x3
06
x7
08
1?
x=
b0x00xx0 !
02
0:
1>
x1
1<
00
0B
0D
0C
0(
1)
b101010 $
b101010 %
#43
x7
x8
x4
x6
03
x?
b0xxx0x01 !
12
x:
x>
0<
x0
0=
1B
11
1C
1D
1(
b101011 $
b101011 %
#44
x9
x5
x8
x3
x6
x=
x>
1?
x1
x0
bx0 !
02
0:
1<
0D
1C
0B
0(
0)
1*
b101100 $
b101100 %
#45
09
08
05
03
x?
b0xx0x01 !
12
x:
1>
0<
00
0=
1B
11
0C
1D
1(
b101101 $
b101101 %
#46
08
x3
x6
x?
x=
b0xx0xx1 !
12
x:
1>
x1
0<
00
1B
0D
0C
0(
1)
b101110 $
b101110 %
#47
x8
06
03
1?
b0xx00x00 !
02
0:
x>
1<
x0
0=
0B
11
1C
1D
1(
b101111 $
b101111 %
#48
14
08
09
03
06
1>
1?
x5
00
0:
b0x0x101 !
12
x@
0C
0B
0<
x;
0(
0)
0*
0+
1,
b110000 $
b110000 %
#49
x6
x8
x9
x4
x3
x?
bx0 !
02
x:
x>
1<
x0
x=
1B
x1
1C
0D
1(
b110001 $
b110001 %
#50
x4
x3
x8
x?
0=
bx0 !
02
x:
x>
11
1<
x0
1B
1D
1C
0(
1)
b110010 $
b110010 %
#51
x9
x6
08
1?
bx0xxxxx1 !
12
0:
1>
0<
00
x=
0B
x1
0C
0D
1(
b110011 $
b110011 %
#52
03
x8
0=
1>
x?
11
00
bx00 !
02
x:
1<
1D
0C
1B
0(
0)
1*
b110100 $
b110100 %
#53
x3
1?
bx1 !
12
0:
x>
0<
x0
x=
0B
x1
1C
0D
1(
b110101 $
b110101 %
#54
09
x3
1?
0=
b0xxxxxx1 !
12
0:
x>
11
0<
x0
0B
1D
1C
0(
1)
b110110 $
b110110 %
#55
x9
x?
bx0 !
02
x:
1>
1<
00
x=
1B
x1
0C
0D
1(
b110111 $
b110111 %
#56
09
06
14
08
03
0=
1>
1?
11
00
0:
b0x0x100 !
02
1D
0C
0B
1<
0(
0)
0*
1+
b111000 $
b111000 %
#57
x6
x8
x9
x4
x3
x?
bx1 !
12
x:
x>
0<
x0
x=
1B
x1
1C
0D
1(
b111001 $
b111001 %
#58
x4
x3
x8
x?
0=
bx1 !
12
x:
x>
11
0<
x0
1B
1D
1C
0(
1)
b111010 $
b111010 %
#59
x9
x6
08
1?
bx0xxxxx0 !
02
0:
1>
1<
00
x=
0B
x1
0C
0D
1(
b111011 $
b111011 %
#60
03
x8
0=
1>
x?
11
00
bx01 !
12
x:
0<
1D
0C
1B
0(
0)
1*
b111100 $
b111100 %
#61
x3
1?
bx0 !
02
0:
x>
1<
x0
x=
0B
x1
1C
0D
1(
b111101 $
b111101 %
#62
09
x3
1?
0=
b0xxxxxx0 !
02
0:
x>
11
1<
x0
0B
1D
1C
0(
1)
b111110 $
b111110 %
#63
x9
x?
bx1 !
12
x:
1>
0<
00
x=
1B
x1
0C
0D
1(
b111111 $
b111111 %
#64
bx0 !
02
1@
1=
x>
1<
0;
01
x0
0(
0)
0*
0+
0,
0-
1.
b1000000 $
b1000000 %
#65
07
04
03
1?
bx0xx001 !
12
0:
0>
0<
10
x=
0B
x1
1C
1D
1(
b1000001 $
b1000001 %
#66
16
15
19
08
07
03
04
1?
1=
b10011001 !
12
0:
0>
01
0<
10
0B
0D
1C
0(
1)
b1000010 $
b1000010 %
#67
x6
x9
x3
x7
x8
x5
x4
x?
bx0 !
02
x:
x>
1<
x0
x=
1B
x1
0C
1D
1(
b1000011 $
b1000011 %
#68
07
04
08
x3
1=
x>
1?
01
x0
bx00xx0x1 !
12
0:
0<
0D
0C
0B
0(
0)
1*
b1000100 $
b1000100 %
#69
03
x7
x8
x4
x?
bx00 !
02
x:
0>
1<
10
x=
1B
x1
1C
1D
1(
b1000101 $
b1000101 %
#70
x6
19
x5
03
x4
x7
x?
1=
b1xxxxx00 !
02
x:
0>
01
1<
10
1B
0D
1C
0(
1)
b1000110 $
b1000110 %
#71
x9
x3
x4
1?
bx1 !
12
0:
x>
0<
x0
x=
0B
x1
0C
1D
1(
b1000111 $
b1000111 %
#72
x3
x4
x7
1=
x>
x?
01
x0
x:
bx1 !
12
0D
0C
1B
0<
0(
0)
0*
1+
b1001000 $
b1001000 %
#73
07
04
03
1?
bx0xx000 !
02
0:
0>
1<
10
x=
0B
x1
1C
1D
1(
b1001001 $
b1001001 %
#74
16
15
19
08
07
03
04
1?
1=
b10011000 !
02
0:
0>
01
1<
10
0B
0D
1C
0(
1)
b1001010 $
b1001010 %
#75
x6
x9
x3
x7
x8
x5
x4
x?
bx1 !
12
x:
x>
0<
x0
x=
1B
x1
0C
1D
1(
b1001011 $
b1001011 %
#76
07
04
08
x3
1=
x>
1?
01
x0
bx00xx0x0 !
02
0:
1<
0D
0C
0B
0(
0)
1*
b1001100 $
b1001100 %
#77
03
x7
x8
x4
x?
bx01 !
12
x:
0>
0<
10
x=
1B
x1
1C
1D
1(
b1001101 $
b1001101 %
#78
x6
19
x5
03
x4
x7
x?
1=
b1xxxxx01 !
12
x:
0>
01
0<
10
1B
0D
1C
0(
1)
b1001110 $
b1001110 %
#79
x9
x3
x4
1?
bx0 !
02
0:
x>
1<
x0
x=
0B
x1
0C
1D
1(
b1001111 $
b1001111 %
#80
07
0>
1?
10
0:
bx0xxxx1 !
12
x@
1C
0B
0<
x;
0(
0)
0*
0+
1,
b1010000 $
b1010000 %
#81
x7
x3
x?
bx0 !
02
x:
x>
1<
x0
1=
1B
01
0C
0D
1(
b1010001 $
b1010001 %
#82
x?
x=
bx0 !
02
x:
x>
x1
1<
x0
1B
1D
0C
0(
1)
b1010010 $
b1010010 %
#83
04
15
03
07
1?
bx0x1001 !
12
0:
0>
0<
10
1=
0B
01
1C
0D
1(
b1010011 $
b1010011 %
#84
x3
x7
x5
x4
x=
0>
x?
x1
10
bx0 !
02
x:
1<
1D
1C
1B
0(
0)
1*
b1010100 $
b1010100 %
#85
07
x4
x3
1?
bx0xxxx1 !
12
0:
x>
0<
x0
1=
0B
01
0C
0D
1(
b1010101 $
b1010101 %
#86
x5
x7
1?
x=
bx1 !
12
0:
x>
x1
0<
x0
0B
1D
0C
0(
1)
b1010110 $
b1010110 %
#87
03
x5
x?
bx00 !
02
x:
0>
1<
10
1=
1B
01
1C
0D
1(
b1010111 $
b1010111 %
#88
07
x3
x4
x=
0>
1?
x1
10
0:
bx0xxxx0 !
02
1D
1C
0B
1<
0(
0)
0*
1+
b1011000 $
b1011000 %
#89
x7
x3
x?
bx1 !
12
x:
x>
0<
x0
1=
1B
01
0C
0D
1(
b1011001 $
b1011001 %
#90
x?
x=
bx1 !
12
x:
x>
x1
0<
x0
1B
1D
0C
0(
1)
b1011010 $
b1011010 %
#91
04
15
03
07
1?
bx0x1000 !
02
0:
0>
1<
10
1=
0B
01
1C
0D
1(
b1011011 $
b1011011 %
#92
x3
x7
x5
x4
x=
0>
x?
x1
10
bx1 !
12
x:
0<
1D
1C
1B
0(
0)
1*
b1011100 $
b1011100 %
#93
07
x4
x3
1?
bx0xxxx0 !
02
0:
x>
1<
x0
1=
0B
01
0C
0D
1(
b1011101 $
b1011101 %
#94
x5
x7
1?
x=
bx0 !
02
0:
x>
x1
1<
x0
0B
1D
0C
0(
1)
b1011110 $
b1011110 %
#95
03
x5
x?
bx01 !
12
x:
0>
0<
10
1=
1B
01
1C
0D
1(
b1011111 $
b1011111 %
#96
07
04
1?
0:
bx0xx001 !
12
1@
x=
0B
0<
0;
x1
0(
0)
0*
0+
0,
1-
b1100000 $
b1100000 %
#97
x4
09
x7
05
x?
b0xxx0x00 !
02
x:
x>
1<
x0
0=
1B
11
0C
1D
1(
b1100001 $
b1100001 %
#98
x3
x9
x5
x6
x7
x8
x?
x=
bx0 !
02
x:
x>
x1
1<
x0
1B
0D
0C
0(
1)
b1100010 $
b1100010 %
#99
06
04
09
07
18
05
03
1?
b1000001 !
12
0:
0>
0<
10
0=
0B
11
1C
1D
1(
b1100011 $
b1100011 %
#100
x6
x9
x5
03
x4
x8
x7
x=
0>
x?
x1
10
bx00 !
02
x:
1<
0D
1C
1B
0(
0)
1*
b1100100 $
b1100100 %
#101
06
09
05
x4
1?
b0xx00x01 !
12
0:
x>
0<
x0
0=
0B
11
0C
1D
1(
b1100101 $
b1100101 %
#102
x6
x9
x3
x4
x5
x8
1?
x=
bx1 !
12
0:
x>
x1
0<
x0
0B
0D
0C
0(
1)
b1100110 $
b1100110 %
#103
06
04
09
18
05
03
x?
b1x00000 !
02
x:
0>
1<
10
0=
1B
11
1C
1D
1(
b1100111 $
b1100111 %
#104
x9
x5
03
04
x6
x8
07
x=
0>
1?
x1
10
0:
bx0xx000 !
02
0D
1C
0B
1<
0(
0)
0*
1+
b1101000 $
b1101000 %
#105
x4
09
x7
05
x?
b0xxx0x01 !
12
x:
x>
0<
x0
0=
1B
11
0C
1D
1(
b1101001 $
b1101001 %
#106
x3
x9
x5
x6
x7
x8
x?
x=
bx1 !
12
x:
x>
x1
0<
x0
1B
0D
0C
0(
1)
b1101010 $
b1101010 %
#107
06
04
09
07
18
05
03
1?
b1000000 !
02
0:
0>
1<
10
0=
0B
11
1C
1D
1(
b1101011 $
b1101011 %
#108
x6
x9
x5
03
x4
x8
x7
x=
0>
x?
x1
10
bx01 !
12
x:
0<
0D
1C
1B
0(
0)
1*
b1101100 $
b1101100 %
#109
06
09
05
x4
1?
b0xx00x00 !
02
0:
x>
1<
x0
0=
0B
11
0C
1D
1(
b1101101 $
b1101101 %
#110
x6
x9
x3
x4
x5
x8
1?
x=
bx0 !
02
0:
x>
x1
1<
x0
0B
0D
0C
0(
1)
b1101110 $
b1101110 %
#111
06
04
09
18
05
03
x?
b1x00001 !
12
x:
0>
0<
10
0=
1B
11
1C
1D
1(
b1101111 $
b1101111 %
#112
x9
x8
x4
x7
x3
x6
x>
x?
x5
x0
x:
bx0 !
02
x@
0C
1B
1<
x;
0(
0)
0*
0+
1,
b1110000 $
b1110000 %
#113
07
1?
bx0xxxx1 !
12
0:
0>
0<
10
x=
0B
x1
1C
0D
1(
b1110001 $
b1110001 %
#114
09
07
1?
0=
b0x0xxxx1 !
12
0:
0>
11
0<
10
0B
1D
1C
0(
1)
b1110010 $
b1110010 %
#115
x7
x9
x?
bx0 !
02
x:
x>
1<
x0
x=
1B
x1
0C
0D
1(
b1110011 $
b1110011 %
#116
09
0=
x>
1?
11
x0
b0xxxxxx1 !
12
0:
0<
1D
0C
0B
0(
0)
1*
b1110100 $
b1110100 %
#117
x9
x?
bx0 !
02
x:
0>
1<
10
x=
1B
x1
1C
0D
1(
b1110101 $
b1110101 %
#118
09
x?
0=
b0xxxxxx0 !
02
x:
0>
11
1<
10
1B
1D
1C
0(
1)
b1110110 $
b1110110 %
#119
x9
1?
bx1 !
12
0:
x>
0<
x0
x=
0B
x1
0C
0D
1(
b1110111 $
b1110111 %
#120
0=
x>
x?
11
x0
x:
bx1 !
12
1D
0C
1B
0<
0(
0)
0*
1+
b1111000 $
b1111000 %
#121
07
1?
bx0xxxx0 !
02
0:
0>
1<
10
x=
0B
x1
1C
0D
1(
b1111001 $
b1111001 %
#122
09
07
1?
0=
b0x0xxxx0 !
02
0:
0>
11
1<
10
0B
1D
1C
0(
1)
b1111010 $
b1111010 %
#123
x7
x9
x?
bx1 !
12
x:
x>
0<
x0
x=
1B
x1
0C
0D
1(
b1111011 $
b1111011 %
#124
09
0=
x>
1?
11
x0
b0xxxxxx0 !
02
0:
1<
1D
0C
0B
0(
0)
1*
b1111100 $
b1111100 %
#125
x9
x?
bx1 !
12
x:
0>
0<
10
x=
1B
x1
1C
0D
1(
b1111101 $
b1111101 %
#126
09
x?
0=
b0xxxxxx1 !
12
x:
0>
11
0<
10
1B
1D
1C
0(
1)
b1111110 $
b1111110 %
#127
x9
1?
bx0 !
02
0:
x>
1<
x0
x=
0B
x1
0C
0D
1(
b1111111 $
b1111111 %
#128
09
06
04
07
08
b0x0 !
05
1@
1=
1>
x?
0;
01
00
x:
0(
0)
0*
0+
0,
0-
0.
1/
b10000000 $
b10000000 %
#129
03
x7
x8
x6
x9
05
x4
0?
bx0x01 !
12
1:
x>
0<
x0
x=
1B
x1
1C
1D
1(
b10000001 $
b10000001 %
#130
05
03
06
x4
x7
x8
x9
0?
1=
bx00x01 !
12
1:
x>
01
0<
x0
1B
0D
1C
0(
1)
b10000010 $
b10000010 %
#131
x3
09
x7
08
x6
x4
x?
b0xx0xx0 !
02
x:
1>
1<
00
x=
0B
x1
0C
1D
1(
b10000011 $
b10000011 %
#132
07
04
06
08
09
03
1=
1>
0?
01
00
b1 !
12
1:
0<
0D
0C
1B
0(
0)
1*
b10000100 $
b10000100 %
#133
x5
x3
x7
x8
x6
x9
x4
x?
bx0 !
02
x:
x>
1<
x0
x=
0B
x1
1C
1D
1(
b10000101 $
b10000101 %
#134
x6
x3
x5
x7
x8
x9
x?
1=
bx0 !
02
x:
x>
01
1<
x0
0B
0D
1C
0(
1)
b10000110 $
b10000110 %
#135
07
04
03
09
08
05
0?
b0x0001 !
12
1:
1>
0<
00
x=
1B
x1
0C
1D
1(
b10000111 $
b10000111 %
#136
07
06
04
08
09
05
x3
1=
1>
x?
01
00
x:
b0x1 !
12
0D
0C
0B
0<
0(
0)
0*
1+
b10001000 $
b10001000 %
#137
03
x7
x8
x6
x9
05
x4
0?
bx0x00 !
02
1:
x>
1<
x0
x=
1B
x1
1C
1D
1(
b10001001 $
b10001001 %
#138
05
03
06
x4
x7
x8
x9
0?
1=
bx00x00 !
02
1:
x>
01
1<
x0
1B
0D
1C
0(
1)
b10001010 $
b10001010 %
#139
x3
09
x7
08
x6
x4
x?
b0xx0xx1 !
12
x:
1>
0<
00
x=
0B
x1
0C
1D
1(
b10001011 $
b10001011 %
#140
07
04
06
08
09
03
1=
1>
0?
01
00
b0 !
02
1:
1<
0D
0C
1B
0(
0)
1*
b10001100 $
b10001100 %
#141
x5
x3
x7
x8
x6
x9
x4
x?
bx1 !
12
x:
x>
0<
x0
x=
0B
x1
1C
1D
1(
b10001101 $
b10001101 %
#142
x6
x3
x5
x7
x8
x9
x?
1=
bx1 !
12
x:
x>
01
0<
x0
0B
0D
1C
0(
1)
b10001110 $
b10001110 %
#143
07
04
03
09
08
05
0?
b0x0000 !
02
1:
1>
1<
00
x=
1B
x1
0C
1D
1(
b10001111 $
b10001111 %
#144
x4
x7
03
x9
x5
x8
x>
0?
x0
1:
bx01 !
12
x@
1C
1B
0<
x;
0(
0)
0*
0+
1,
b10010000 $
b10010000 %
#145
07
x3
x9
x6
08
x4
x?
bx00xxxx0 !
02
x:
1>
1<
00
1=
0B
01
0C
0D
1(
b10010001 $
b10010001 %
#146
x3
x7
x8
x?
x=
bx0 !
02
x:
1>
x1
1<
00
0B
1D
0C
0(
1)
b10010010 $
b10010010 %
#147
06
03
0?
bx0xx01 !
12
1:
x>
0<
x0
1=
1B
01
1C
0D
1(
b10010011 $
b10010011 %
#148
x6
x8
x3
x=
x>
x?
x1
x0
bx0 !
02
x:
1<
1D
1C
0B
0(
0)
1*
b10010100 $
b10010100 %
#149
09
06
04
08
03
07
0?
b0x001 !
12
1:
1>
0<
00
1=
1B
01
0C
0D
1(
b10010101 $
b10010101 %
#150
03
x6
04
07
x8
x9
0?
x=
bx0xx001 !
12
1:
1>
x1
0<
00
1B
1D
0C
0(
1)
b10010110 $
b10010110 %
#151
x7
x3
x6
x4
x?
bx0 !
02
x:
x>
1<
x0
1=
0B
01
1C
0D
1(
b10010111 $
b10010111 %
#152
03
x=
x>
0?
x1
x0
1:
bx00 !
02
1D
1C
1B
1<
0(
0)
0*
1+
b10011000 $
b10011000 %
#153
07
x3
x9
x6
08
x4
x?
bx00xxxx1 !
12
x:
1>
0<
00
1=
0B
01
0C
0D
1(
b10011001 $
b10011001 %
#154
x3
x7
x8
x?
x=
bx1 !
12
x:
1>
x1
0<
00
0B
1D
0C
0(
1)
b10011010 $
b10011010 %
