lab_ultra/top.v
module top(switch,signal,clk_in,trigger,l_a,l_b,l_c,l_d,l_e);
	input switch;
	input signal;
	input clk_in;
	output trigger;
	output l_a;
	output l_b;
	output l_c;
	output l_d;
	output l_e;
	parameter SIZE = 17; 
	parameter LIMIT = 17'd1000;
	parameter MAX = 17'd131071;
	parameter ONE = 17'd1;
	parameter ZERO = 17'd0;
	parameter LIMIT2 = 17'd117648;
	parameter MARC10 = 17'd29412;
	parameter MARC20 = 17'd52824;
	parameter MARC30 = 17'd88235;
	reg [SIZE-1:0] count_0 = ZERO;
	reg [SIZE-1:0] count_1 = ZERO;
	reg ti_on = 0;
	reg ul_on = 0;
	reg ul_off= 0;
	reg a = 0;
	reg b = 0;
	reg c = 0;
	reg d = 0;
	reg e = 0;
	assign l_a= ~a;
	assign l_b= ~b;
	assign l_c= ~c;
	assign l_d= ~d;
	assign l_e= ~e;
	assign trigger = ti_on;
	always @(posedge clk_in,posedge switch,posedge signal)
		begin
			if(switch)
				begin
					ti_on <= 1;
				end
			if(ti_on)
				begin
					if (count_0 == LIMIT)
						begin
							ul_on <= 1;	
							ti_on <= 0;
						end
					else
							count_0 <= count_0+ONE;		
				end
			if(ul_on)
				begin
					if (ul_off)
						begin
							ul_on <= 0;
						end
					else if(count_1 == MAX)
						begin
							ul_on <= 0;
						end
					else
						count_1 <= count_1 + ONE;
				end
			if(signal)
				begin
					ul_off <= 1;
				end
			if(ul_off)
				begin
					if (count_1==ZERO)
						begin
							a <= a;
							b <= b;
							c <= c;
							d <= d;
							e <= e;
						end
					else if (count_1 >= LIMIT2)
						begin
							a <= 1;
							b <= 0;
							c <= 0;
							d <= 0;
							e <= 0;
							count_1 <= ZERO;
							ul_off <= 0;
							count_0 <= ZERO;
						end	
					else
						begin
							if(count_1 <= MARC30)
								begin
									if(count_1 <= MARC20)
										begin
											if(count_1 <= MARC10)
												begin
													a <= 0;
													b <= 0;
													c <= 0;
													d <= 0;
													e <= 1;
													count_1 <= ZERO;
													ul_off <= 0;
													count_0 <= ZERO;
												end
											else
												begin
													a <= 0;
													b <= 0;
													c <= 0;
													d <= 1;
													e <= 0;
													count_1 <= ZERO;
													ul_off <= 0;
													count_0 <= ZERO;
												end
										end
									else
										begin
											a <= 0;
											b <= 0;
											c <= 1;
											d <= 0;
											e <= 0;
											count_1 <= ZERO;
											ul_off <= 0;
											count_0 <= ZERO;
										end
								end
							else
								begin
									a <= 0;
									b <= 1;
									c <= 0;
									d <= 0;
									e <= 0;
									count_1 <= ZERO;
									ul_off <= 0;
									count_0 <= ZERO;
								end
						end		
				end
		
		end
endmodule

lab_ultra/top_tb.v
`timescale 10ns/10ns // <time_unit>/<time_precision
module testbech;

  // // Determinar el tamaño de los wire como de los estímulos
  //parameter INPUT_SIZE = 1;
  parameter OUTPUT_SIZE = 6;

  // // STIMULUS 1
   reg at = 0, bt = 0;
   initial
   begin
      #1 at = 1; 
      #2 at = 0; 
      #200000 bt=1;
      #200002 bt=0;
         //   # 100 $finish(); // [stop(), $finish()]
   end

  // // STIMULUS 2
   //reg [INPUT_SIZE-1:0] inputs;
  // inputs[2] inputs[1] inputs[1]
   //integer i;
  // initial
  // begin
     //inputs = 0;
     //for (i=0; i<2**INPUT_SIZE; i=i+1) // 2 elevado a la INPUT_SIZE , en el ejemplo 2^3 = 8 combinaciones
     //begin
       //inputs = i;
       //#1;
     //end
   //end

  // // STIMULUS ARGS
  // initial
  // begin
  //   if(! $value$plusargs("inputs=%b", inputs)) begin
  //     $display("ERROR: please specify +inputs=<value> to start.");
  //     $finish;
  //   end

  //   wait (outs) $display("outs = %d", outs);
  //   #1
  //   $finish;
  // end

  // // CLOCK STIMULUS
  // Make a regular pulsing clock.
  reg clk = 0;
  always #2 clk = !clk;

  initial
   begin
     //#2E4 $stop();
     #300000 $finish(); // [stop(), $finish()]
   end

  // // RESULT FOR DEVICE/DESIGN UNDER TEST
  wire [OUTPUT_SIZE-1:0]value;

  // // DEVICE/DESIGN UNDER TEST
  //sumcomplete (in_a,in_b,op,clk_in,a,b,c,d,e,f,g,sign0,dis1,dis0
  top dut(.switch(at),.signal(bt),.clk_in(clk),.trigger(value[5]),.l_a(value[4]),.l_b(value[3]),.l_c(value[2]),.l_d(value[1]),.l_e(value[0]));
  

  // // MONITOR
  // initial
    // $monitor("Time: %t, a = %d, b = %d => out = %d",
    //   $time, a, b, value);

  // // WAVES IN VCD TO OPEN IN GTKWAVE
  initial
  begin
    $dumpfile("top.vcd");
    $dumpvars(0, testbech);
  end
endmodule

lab_ultra/sim/top.vcd
$date
	Thu Nov 30 10:11:47 2023
$end
$version
	Icarus Verilog
$end
$timescale
	10ns
$end
$scope module testbech $end
$var wire 6 ! value [5:0] $end
$var parameter 32 " OUTPUT_SIZE $end
$var reg 1 # at $end
$var reg 1 $ bt $end
$var reg 1 % clk $end
$scope module dut $end
$var wire 1 % clk_in $end
$var wire 1 & l_a $end
$var wire 1 ' l_b $end
$var wire 1 ( l_c $end
$var wire 1 ) l_d $end
$var wire 1 * l_e $end
$var wire 1 $ signal $end
$var wire 1 # switch $end
$var wire 1 + trigger $end
$var parameter 17 , LIMIT $end
$var parameter 17 - LIMIT2 $end
$var parameter 17 . MARC10 $end
$var parameter 17 / MARC20 $end
$var parameter 17 0 MARC30 $end
$var parameter 17 1 MAX $end
$var parameter 17 2 ONE $end
$var parameter 32 3 SIZE $end
$var parameter 17 4 ZERO $end
$var reg 1 5 a $end
$var reg 1 6 b $end
$var reg 1 7 c $end
$var reg 17 8 count_0 [16:0] $end
$var reg 17 9 count_1 [16:0] $end
$var reg 1 : d $end
$var reg 1 ; e $end
$var reg 1 + ti_on $end
$var reg 1 < ul_off $end
$var reg 1 = ul_on $end
$upscope $end
$upscope $end
$enddefinitions $end
$comment Show the parameter values. $end
$dumpall
b0 4
b10001 3
b1 2
b11111111111111111 1
b10101100010101011 0
b1100111001011000 /
b111001011100100 .
b11100101110010000 -
b1111101000 ,
b110 "
$end
#0
$dumpvars
0=
0<
0;
0:
b0 9
b0 8
07
06
05
0+
1*
1)
1(
1'
1&
0%
0$
0#
b11111 !
$end
#1
b111111 !
1+
1#
#2
b1 8
1%
#3
0#
#4
0%
#6
b10 8
1%
#8
0%
#10
b11 8
1%
#12
0%
#14
b100 8
1%
#16
0%
#18
b101 8
1%
#20
0%
#22
b110 8
1%
#24
0%
#26
b111 8
1%
#28
0%
#30
b1000 8
1%
#32
0%
#34
b1001 8
1%
#36
0%
#38
b1010 8
1%
#40
0%
#42
b1011 8
1%
#44
0%
#46
b1100 8
1%
#48
0%
#50
b1101 8
1%
#52
0%
#54
b1110 8
1%
#56
0%
#58
b1111 8
1%
#60
0%
#62
b10000 8
1%
#64
0%
#66
b10001 8
1%
#68
0%
#70
b10010 8
1%
#72
0%
#74
b10011 8
1%
#76
0%
#78
b10100 8
1%
#80
0%
#82
b10101 8
1%
#84
0%
#86
b10110 8
1%
#88
0%
#90
b10111 8
1%
#92
0%
#94
b11000 8
1%
#96
0%
#98
b11001 8
1%
#100
0%
#102
b11010 8
1%
#104
0%
#106
b11011 8
1%
#108
0%
#110
b11100 8
1%
#112
0%
#114
b11101 8
1%
#116
0%
#118
b11110 8
1%
#120
0%
#122
b11111 8
1%
#124
0%
#126
b100000 8
1%
#128
0%
#130
b100001 8
1%
#132
0%
#134
b100010 8
1%
#136
0%
#138
b100011 8
1%
#140
0%
#142
b100100 8
1%
#144
0%
#146
b100101 8
1%
#148
0%
#150
b100110 8
1%
#152
0%
#154
b100111 8
1%
#156
0%
#158
b101000 8
1%
#160
0%
#162
b101001 8
1%
#164
0%
#166
b101010 8
1%
#168
0%
#170
b101011 8
1%
#172
0%
#174
b101100 8
1%
#176
0%
#178
b101101 8
1%
#180
0%
#182
b101110 8
1%
#184
0%
#186
b101111 8
1%
#188
0%
#190
b110000 8
1%
#192
0%
#194
b110001 8
1%
#196
0%
#198
b110010 8
1%
#200
0%
#202
b110011 8
1%
#204
0%
#206
b110100 8
1%
#208
0%
#210
b110101 8
1%
#212
0%
#214
b110110 8
1%
#216
0%
#218
b110111 8
1%
#220
0%
#222
b111000 8
1%
#224
0%
#226
b111001 8
1%
#228
0%
#230
b111010 8
1%
#232
0%
#234
b111011 8
1%
#236
0%
#238
b111100 8
1%
#240
0%
#242
b111101 8
1%
#244
0%
#246
b111110 8
1%
#248
0%
#250
b111111 8
1%
#252
0%
#254
b1000000 8
1%
#256
0%
#258
b1000001 8
1%
#260
0%
#262
b1000010 8
1%
#264
0%
#266
b1000011 8
1%
#268
0%
#270
b1000100 8
1%
#272
0%
#274
b1000101 8
1%
#276
0%
#278
b1000110 8
1%
#280
0%
#282
b1000111 8
1%
#284
0%
#286
b1001000 8
1%
#288
0%
#290
b1001001 8
1%
#292
0%
#294
b1001010 8
1%
#296
0%
#298
b1001011 8
1%
#300
0%
#302
b1001100 8
1%
#304
0%
#306
b1001101 8
1%
#308
0%
#310
b1001110 8
1%
#312
0%
#314
b1001111 8
1%
#316
0%
#318
b1010000 8
1%
#320
0%
#322
b1010001 8
1%
#324
0%
#326
b1010010 8
1%
#328
0%
#330
b1010011 8
1%
#332
0%
#334
b1010100 8
1%
#336
0%
#338
b1010101 8
1%
#340
0%
#342
b1010110 8
1%
#344
0%
#346
b1010111 8
1%
#348
0%
#350
b1011000 8
1%
#352
0%
#354
b1011001 8
1%
#356
0%
#358
b1011010 8
1%
#360
0%
#362
b1011011 8
1%
#364
0%
#366
b1011100 8
1%
#368
0%
#370
b1011101 8
1%
#372
0%
#374
b1011110 8
1%
#376
0%
#378
b1011111 8
1%
#380
0%
#382
b1100000 8
1%
#384
0%
#386
b1100001 8
1%
#388
0%
#390
b1100010 8
1%
#392
0%
#394
b1100011 8
1%
#396
0%
#398
b1100100 8
1%
#400
0%
#402
b1100101 8
1%
#404
0%
#406
b1100110 8
1%
#408
0%
#410
b1100111 8
1%
#412
0%
#414
b1101000 8
1%
#416
0%
#418
b1101001 8
1%
#420
0%
#422
b1101010 8
1%
#424
0%
#426
b1101011 8
1%
#428
0%
#430
b1101100 8
1%
#432
0%
#434
b1101101 8
1%
#436
0%
#438
b1101110 8
1%
#440
0%
#442
b1101111 8
1%
#444
0%
#446
b1110000 8
1%
#448
0%
#450
b1110001 8
1%
#452
0%
#454
b1110010 8
1%
#456
0%
#458
b1110011 8
1%
#460
0%
#462
b1110100 8
1%
#464
0%
#466
b1110101 8
1%
#468
0%
#470
b1110110 8
1%
#472
0%
#474
b1110111 8
1%
#476
0%
#478
b1111000 8
1%
#480
0%
#482
b1111001 8
1%
#484
0%
#486
b1111010 8
1%
#488
0%
#490
b1111011 8
1%
#492
0%
#494
b1111100 8
1%
#496
0%
#498
b1111101 8
1%
#500
0%
#502
b1111110 8
1%
#504
0%
#506
b1111111 8
1%
#508
0%
#510
b10000000 8
1%
#512
0%
#514
b10000001 8
1%
#516
0%
#518
b10000010 8
1%
#520
0%
#522
b10000011 8
1%
#524
0%
#526
b10000100 8
1%
#528
0%
#530
b10000101 8
1%
#532
0%
#534
b10000110 8
1%
#536
0%
#538
b10000111 8
1%
#540
0%
#542
b10001000 8
1%
#544
0%
#546
b10001001 8
1%
#548
0%
#550
b10001010 8
1%
#552
0%
#554
b10001011 8
1%
#556
0%
#558
b10001100 8
1%
#560
0%
#562
b10001101 8
1%
#564
0%
#566
b10001110 8
1%
#568
0%
#570
b10001111 8
1%
#572
0%
#574
b10010000 8
1%
#576
0%
#578
b10010001 8
1%
#580
0%
#582
b10010010 8
1%
#584
0%
#586
b10010011 8
1%
#588
0%
#590
b10010100 8
1%
#592
0%
#594
b10010101 8
1%
#596
0%
#598
b10010110 8
1%
#600
0%
#602
b10010111 8
1%
#604
0%
#606
b10011000 8
1%
#608
0%
#610
b10011001 8
1%
#612
0%
#614
b10011010 8
1%
#616
0%
#618
b10011011 8
1%
#620
0%
#622
b10011100 8
1%
#624
0%
#626
b10011101 8
1%
#628
0%
#630
b10011110 8
1%
#632
0%
#634
b10011111 8
1%
#636
0%
#638
b10100000 8
1%
#640
0%
#642
b10100001 8
1%
#644
0%
#646
b10100010 8
1%
#648
0%
#650
b10100011 8
1%
#652
0%
#654
b10100100 8
1%
#656
0%
#658
b10100101 8
1%
#660
0%
#662
b10100110 8
1%
#664
0%
#666
b10100111 8
1%
#668
0%
#670
b10101000 8
1%
#672
0%
#674
b10101001 8
1%
#676
0%
#678
b10101010 8
1%
#680
0%
#682
b10101011 8
1%
#684
0%
#686
b10101100 8
1%
#688
0%
#690
b10101101 8
1%
#692
0%
#694
b10101110 8
1%
#696
0%
#698
b10101111 8
1%
#700
0%
#702
b10110000 8
1%
#704
0%
#706
b10110001 8
1%
#708
0%
#710
b10110010 8
1%
#712
0%
#714
b10110011 8
1%
#716
0%
#718
b10110100 8
1%
#720
0%
#722
b10110101 8
1%
#724
0%
#726
b10110110 8
1%
#728
0%
#730
b10110111 8
1%
#732
0%
#734
b10111000 8
1%
#736
0%
#738
b10111001 8
1%
#740
0%
#742
b10111010 8
1%
#744
0%
#746
b10111011 8
1%
#748
0%
#750
b10111100 8
1%
#752
0%
#754
b10111101 8
1%
#756
0%
#758
b10111110 8
1%
#760
0%
#762
b10111111 8
1%
#764
0%
#766
b11000000 8
1%
#768
0%
#770
b11000001 8
1%
#772
0%
#774
b11000010 8
1%
#776
0%
#778
b11000011 8
1%
#780
0%
#782
b11000100 8
1%
#784
0%
#786
b11000101 8
1%
#788
0%
#790
b11000110 8
1%
#792
0%
#794
b11000111 8
1%
#796
0%
#798
b11001000 8
1%
#800
0%
#802
b11001001 8
1%
#804
0%
#806
b11001010 8
1%
#808
0%
#810
b11001011 8
1%
#812
0%
#814
b11001100 8
1%
#816
0%
#818
b11001101 8
1%
#820
0%
#822
b11001110 8
1%
#824
0%
#826
b11001111 8
1%
#828
0%
#830
b11010000 8
1%
#832
0%
#834
b11010001 8
1%
#836
0%
#838
b11010010 8
1%
#840
0%
#842
b11010011 8
1%
#844
0%
#846
b11010100 8
1%
#848
0%
#850
b11010101 8
1%
#852
0%
#854
b11010110 8
1%
#856
0%
#858
b11010111 8
1%
#860
0%
#862
b11011000 8
1%
#864
0%
#866
b11011001 8
1%
#868
0%
#870
b11011010 8
1%
#872
0%
#874
b11011011 8
1%
#876
0%
#878
b11011100 8
1%
#880
0%
#882
b11011101 8
1%
#884
0%
#886
b11011110 8
1%
#888
0%
#890
b11011111 8
1%
#892
0%
#894
b11100000 8
1%
#896
0%
#898
b11100001 8
1%
#900
0%
#902
b11100010 8
1%
#904
0%
#906
b11100011 8
1%
#908
0%
#910
b11100100 8
1%
#912
0%
#914
b11100101 8
1%
#916
0%
#918
b11100110 8
1%
#920
0%
#922
b11100111 8
1%
#924
0%
#926
b11101000 8
1%
#928
0%
#930
b11101001 8
1%
#932
0%
#934
b11101010 8
1%
#936
0%
#938
b11101011 8
1%
#940
0%
#942
b11101100 8
1%
#944
0%
#946
b11101101 8
1%
#948
0%
#950
b11101110 8
1%
#952
0%
#954
b11101111 8
1%
#956
0%
#958
b11110000 8
1%
#960
0%
#962
b11110001 8
1%
#964
0%
#966
b11110010 8
1%
#968
0%
#970
b11110011 8
1%
#972
0%
#974
b11110100 8
1%
#976
0%
#978
b11110101 8
1%
#980
0%
#982
b11110110 8
1%
#984
0%
#986
b11110111 8
1%
#988
0%
#990
b11111000 8
1%
#992
0%
#994
b11111001 8
1%
#996
0%
#998
b11111010 8
1%
#1000
0%
#1002
b11111011 8
1%
#1004
0%
#1006
b11111100 8
1%
#1008
0%
#1010
b11111101 8
1%
#1012
0%
#1014
b11111110 8
1%
#1016
0%
#1018
b11111111 8
1%
#1020
0%
#1022
b100000000 8
1%
#1024
0%
#1026
b100000001 8
1%
#1028
0%
#1030
b100000010 8
1%
#1032
0%
#1034
b100000011 8
1%
#1036
0%
#1038
b100000100 8
1%
#1040
0%
#1042
b100000101 8
1%
#1044
0%
#1046
b100000110 8
1%
#1048
0%
#1050
b100000111 8
1%
#1052
0%
#1054
b100001000 8
1%
#1056
0%
#1058
b100001001 8
1%
#1060
0%
#1062
b100001010 8
1%
#1064
0%
#1066
b100001011 8
1%
#1068
0%
#1070
b100001100 8
1%
#1072
0%
#1074
b100001101 8
1%
#1076
0%
#1078
b100001110 8
1%
#1080
0%
#1082
b100001111 8
1%
#1084
0%
#1086
b100010000 8
1%
#1088
0%
#1090
b100010001 8
1%
#1092
0%
#1094
b100010010 8
1%
#1096
0%
#1098
b100010011 8
1%
#1100
0%
#1102
b100010100 8
1%
#1104
0%
#1106
b100010101 8
1%
#1108
0%
#1110
b100010110 8
1%
#1112
0%
#1114
b100010111 8
1%
#1116
0%
#1118
b100011000 8
1%
#1120
0%
#1122
b100011001 8
1%
#1124
0%
#1126
b100011010 8
1%
#1128
0%
#1130
b100011011 8
1%
#1132
0%
#1134
b100011100 8
1%
#1136
0%
#1138
b100011101 8
1%
#1140
0%
#1142
b100011110 8
1%
#1144
0%
#1146
b100011111 8
1%
#1148
0%
#1150
b100100000 8
1%
#1152
0%
#1154
b100100001 8
1%
#1156
0%
#1158
b100100010 8
1%
#1160
0%
#1162
b100100011 8
1%
#1164
0%
#1166
b100100100 8
1%
#1168
0%
#1170
b100100101 8
1%
#1172
0%
#1174
b100100110 8
1%
#1176
0%
#1178
b100100111 8
1%
#1180
0%
#1182
b100101000 8
1%
#1184
0%
#1186
b100101001 8
1%
#1188
0%
#1190
b100101010 8
1%
#1192
0%
#1194
b100101011 8
1%
#1196
0%
#1198
b100101100 8
1%
#1200
0%
#1202
b100101101 8
1%
#1204
0%
#1206
b100101110 8
1%
#1208
0%
#1210
b100101111 8
1%
#1212
0%
#1214
b100110000 8
1%
#1216
0%
#1218
b100110001 8
1%
#1220
0%
#1222
b100110010 8
1%
#1224
0%
#1226
b100110011 8
1%
#1228
0%
#1230
b100110100 8
1%
#1232
0%
#1234
b100110101 8
1%
#1236
0%
#1238
b100110110 8
1%
#1240
0%
#1242
b100110111 8
1%
#1244
0%
#1246
b100111000 8
1%
#1248
0%
#1250
b100111001 8
1%
#1252
0%
#1254
b100111010 8
1%
#1256
0%
#1258
b100111011 8
1%
#1260
0%
#1262
b100111100 8
1%
#1264
0%
#1266
b100111101 8
1%
#1268
0%
#1270
b100111110 8
1%
#1272
0%
#1274
b100111111 8
1%
#1276
0%
#1278
b101000000 8
1%
#1280
0%
#1282
b101000001 8
1%
#1284
0%
#1286
b101000010 8
1%
#1288
0%
#1290
b101000011 8
1%
#1292
0%
#1294
b101000100 8
1%
#1296
0%
#1298
b101000101 8
1%
#1300
0%
#1302
b101000110 8
1%
#1304
0%
#1306
b101000111 8
1%
#1308
0%
#1310
b101001000 8
1%
#1312
0%
#1314
b101001001 8
1%
#1316
0%
#1318
b101001010 8
1%
#1320
0%
#1322
b101001011 8
1%
#1324
0%
#1326
b101001100 8
1%
#1328
0%
#1330
b101001101 8
1%
#1332
0%
#1334
b101001110 8
1%
#1336
0%
#1338
b101001111 8
1%
#1340
0%
#1342
b101010000 8
1%
#1344
0%
#1346
b101010001 8
1%
#1348
0%
#1350
b101010010 8
1%
#1352
0%
#1354
b101010011 8
1%
#1356
0%
#1358
b101010100 8
1%
#1360
0%
#1362
b101010101 8
1%
#1364
0%
#1366
b101010110 8
1%
#1368
0%
#1370
b101010111 8
1%
#1372
0%
#1374
b101011000 8
1%
#1376
0%
#1378
b101011001 8
1%
#1380
0%
#1382
b101011010 8
1%
#1384
0%
#1386
b101011011 8
1%
#1388
0%
#1390
b101011100 8
1%
#1392
0%
#1394
b101011101 8
1%
#1396
0%
#1398
b101011110 8
1%
#1400
0%
#1402
b101011111 8
1%
#1404
0%
#1406
b101100000 8
1%
#1408
0%
#1410
b101100001 8
1%
#1412
0%
#1414
b101100010 8
1%
#1416
0%
#1418
b101100011 8
1%
#1420
0%
#1422
b101100100 8
1%
#1424
0%
#1426
b101100101 8
1%
#1428
0%
#1430
b101100110 8
1%
#1432
0%
#1434
b101100111 8
1%
#1436
0%
#1438
b101101000 8
1%
#1440
0%
#1442
b101101001 8
1%
#1444
0%
#1446
b101101010 8
1%
#1448
0%
#1450
b101101011 8
1%
#1452
0%
#1454
b101101100 8
1%
#1456
0%
#1458
b101101101 8
1%
#1460
0%
#1462
b101101110 8
1%
#1464
0%
#1466
b101101111 8
1%
#1468
0%
#1470
b101110000 8
1%
#1472
0%
#1474
b101110001 8
1%
#1476
0%
#1478
b101110010 8
1%
#1480
0%
#1482
b101110011 8
1%
#1484
0%
#1486
b101110100 8
1%
#1488
0%
#1490
b101110101 8
1%
#1492
0%
#1494
b101110110 8
1%
#1496
0%
#1498
b101110111 8
1%
#1500
0%
#1502
b101111000 8
1%
#1504
0%
#1506
b101111001 8
1%
#1508
0%
#1510
b101111010 8
1%
#1512
0%
#1514
b101111011 8
1%
#1516
0%
#1518
b101111100 8
1%
#1520
0%
#1522
b101111101 8
1%
#1524
0%
#1526
b101111110 8
1%
#1528
0%
#1530
b101111111 8
1%
#1532
0%
#1534
b110000000 8
1%
#1536
0%
#1538
b110000001 8
1%
#1540
0%
#1542
b110000010 8
1%
#1544
0%
#1546
b110000011 8
1%
#1548
0%
#1550
b110000100 8
1%
#1552
0%
#1554
b110000101 8
1%
#1556
0%
#1558
b110000110 8
1%
#1560
0%
#1562
b110000111 8
1%
#1564
0%
#1566
b110001000 8
1%
#1568
0%
#1570
b110001001 8
1%
#1572
0%
#1574
b110001010 8
1%
#1576
0%
#1578
b110001011 8
1%
#1580
0%
#1582
b110001100 8
1%
#1584
0%
#1586
b110001101 8
1%
#1588
0%
#1590
b110001110 8
1%
#1592
0%
#1594
b110001111 8
1%
#1596
0%
#1598
b110010000 8
1%
#1600
0%
#1602
b110010001 8
1%
#1604
0%
#1606
b110010010 8
1%
#1608
0%
#1610
b110010011 8
1%
#1612
0%
#1614
b110010100 8
1%
#1616
0%
#1618
b110010101 8
1%
#1620
0%
#1622
b110010110 8
1%
#1624
0%
#1626
b110010111 8
1%
#1628
0%
#1630
b110011000 8
1%
#1632
0%
#1634
b110011001 8
1%
#1636
0%
#1638
b110011010 8
1%
#1640
0%
#1642
b110011011 8
1%
#1644
0%
#1646
b110011100 8
1%
#1648
0%
#1650
b110011101 8
1%
#1652
0%
#1654
b110011110 8
1%
#1656
0%
#1658
b110011111 8
1%
#1660
0%
#1662
b110100000 8
1%
#1664
0%
#1666
b110100001 8
1%
#1668
0%
#1670
b110100010 8
1%
#1672
0%
#1674
b110100011 8
1%
#1676
0%
#1678
b110100100 8
1%
#1680
0%
#1682
b110100101 8
1%
#1684
0%
#1686
b110100110 8
1%
#1688
0%
#1690
b110100111 8
1%
#1692
0%
#1694
b110101000 8
1%
#1696
0%
#1698
b110101001 8
1%
#1700
0%
#1702
b110101010 8
1%
#1704
0%
#1706
b110101011 8
1%
#1708
0%
#1710
b110101100 8
1%
#1712
0%
#1714
b110101101 8
1%
#1716
0%
#1718
b110101110 8
1%
#1720
0%
#1722
b110101111 8
1%
#1724
0%
#1726
b110110000 8
1%
#1728
0%
#1730
b110110001 8
1%
#1732
0%
#1734
b110110010 8
1%
#1736
0%
#1738
b110110011 8
1%
#1740
0%
#1742
b110110100 8
1%
#1744
0%
#1746
b110110101 8
1%
#1748
0%
#1750
b110110110 8
1%
#1752
0%
#1754
b110110111 8
1%
#1756
0%
#1758
b110111000 8
1%
#1760
0%
#1762
b110111001 8
1%
#1764
0%
#1766
b110111010 8
1%
#1768
0%
#1770
b110111011 8
1%
#1772
0%
#1774
b110111100 8
1%
#1776
0%
#1778
b110111101 8
1%
#1780
0%
#1782
b110111110 8
1%
#1784
0%
#1786
b110111111 8
1%
#1788
0%
#1790
b111000000 8
1%
#1792
0%
#1794
b111000001 8
1%
#1796
0%
#1798
b111000010 8
1%
#1800
0%
#1802
b111000011 8
1%
#1804
0%
#1806
b111000100 8
1%
#1808
0%
#1810
b111000101 8
1%
#1812
0%
#1814
b111000110 8
1%
#1816
0%
#1818
b111000111 8
1%
#1820
0%
#1822
b111001000 8
1%
#1824
0%
#1826
b111001001 8
1%
#1828
0%
#1830
b111001010 8
1%
#1832
0%
#1834
b111001011 8
1%
#1836
0%
#1838
b111001100 8
1%
#1840
0%
#1842
b111001101 8
1%
#1844
0%
#1846
b111001110 8
1%
#1848
0%
#1850
b111001111 8
1%
#1852
0%
#1854
b111010000 8
1%
#1856
0%
#1858
b111010001 8
1%
#1860
0%
#1862
b111010010 8
1%
#1864
0%
#1866
b111010011 8
1%
#1868
0%
#1870
b111010100 8
1%
#1872
0%
#1874
b111010101 8
1%
#1876
0%
#1878
b111010110 8
1%
#1880
0%
#1882
b111010111 8
1%
#1884
0%
#1886
b111011000 8
1%
#1888
0%
#1890
b111011001 8
1%
#1892
0%
#1894
b111011010 8
1%
#1896
0%
#1898
b111011011 8
1%
#1900
0%
#1902
b111011100 8
1%
#1904
0%
#1906
b111011101 8
1%
#1908
0%
#1910
b111011110 8
1%
#1912
0%
#1914
b111011111 8
1%
#1916
0%
#1918
b111100000 8
1%
#1920
0%
#1922
b111100001 8
1%
#1924
0%
#1926
b111100010 8
1%
#1928
0%
#1930
b111100011 8
1%
#1932
0%
#1934
b111100100 8
1%
#1936
0%
#1938
b111100101 8
1%
#1940
0%
#1942
b111100110 8
1%
#1944
0%
#1946
b111100111 8
1%
#1948
0%
#1950
b111101000 8
1%
#1952
0%
#1954
b111101001 8
1%
#1956
0%
#1958
b111101010 8
1%
#1960
0%
#1962
b111101011 8
1%
#1964
0%
#1966
b111101100 8
1%
#1968
0%
#1970
b111101101 8
1%
#1972
0%
#1974
b111101110 8
1%
#1976
0%
#1978
b111101111 8
1%
#1980
0%
#1982
b111110000 8
1%
#1984
0%
#1986
b111110001 8
1%
#1988
0%
#1990
b111110010 8
1%
#1992
0%
#1994
b111110011 8
1%
#1996
0%
#1998
b111110100 8
1%
#2000
0%
#2002
b111110101 8
1%
#2004
0%
#2006
b111110110 8
1%
#2008
0%
#2010
b111110111 8
1%
#2012
0%
#2014
b111111000 8
1%
#2016
0%
#2018
b111111001 8
1%
#2020
0%
#2022
b111111010 8
1%
#2024
0%
#2026
b111111011 8
1%
#2028
0%
#2030
b111111100 8
1%
#2032
0%
#2034
b111111101 8
1%
#2036
0%
#2038
b111111110 8
1%
#2040
0%
#2042
b111111111 8
1%
#2044
0%
#2046
b1000000000 8
1%
#2048
0%
#2050
b1000000001 8
1%
#2052
0%
#2054
b1000000010 8
1%
#2056
0%
#2058
b1000000011 8
1%
#2060
0%
#2062
b1000000100 8
1%
#2064
0%
#2066
b1000000101 8
1%
#2068
0%
#2070
b1000000110 8
1%
#2072
0%
#2074
b1000000111 8
1%
#2076
0%
#2078
b1000001000 8
1%
#2080
0%
#2082
b1000001001 8
1%
#2084
0%
#2086
b1000001010 8
1%
#2088
0%
#2090
b1000001011 8
1%
#2092
0%
#2094
b1000001100 8
1%
#2096
0%
#2098
b1000001101 8
1%
#2100
0%
#2102
b1000001110 8
1%
#2104
0%
#2106
b1000001111 8
1%
#2108
0%
#2110
b1000010000 8
1%
#2112
0%
#2114
b1000010001 8
1%
#2116
0%
#2118
b1000010010 8
1%
#2120
0%
#2122
b1000010011 8
1%
#2124
0%
#2126
b1000010100 8
1%
#2128
0%
#2130
b1000010101 8
1%
#2132
0%
#2134
b1000010110 8
1%
#2136
0%
#2138
b1000010111 8
1%
#2140
0%
#2142
b1000011000 8
1%
#2144
0%
#2146
b1000011001 8
1%
#2148
0%
#2150
b1000011010 8
1%
#2152
0%
#2154
b1000011011 8
1%
#2156
0%
#2158
b1000011100 8
1%
#2160
0%
#2162
b1000011101 8
1%
#2164
0%
#2166
b1000011110 8
1%
#2168
0%
#2170
b1000011111 8
1%
#2172
0%
#2174
b1000100000 8
1%
#2176
0%
#2178
b1000100001 8
1%
#2180
0%
#2182
b1000100010 8
1%
#2184
0%
#2186
b1000100011 8
1%
#2188
0%
#2190
b1000100100 8
1%
#2192
0%
#2194
b1000100101 8
1%
#2196
0%
#2198
b1000100110 8
1%
#2200
0%
#2202
b1000100111 8
1%
#2204
0%
#2206
b1000101000 8
1%
#2208
0%
#2210
b1000101001 8
1%
#2212
0%
#2214
b1000101010 8
1%
#2216
0%
#2218
b1000101011 8
1%
#2220
0%
#2222
b1000101100 8
1%
#2224
0%
#2226
b1000101101 8
1%
#2228
0%
#2230
b1000101110 8
1%
#2232
0%
#2234
b1000101111 8
1%
#2236
0%
#2238
b1000110000 8
1%
#2240
0%
#2242
b1000110001 8
1%
#2244
0%
#2246
b1000110010 8
1%
#2248
0%
#2250
b1000110011 8
1%
#2252
0%
#2254
b1000110100 8
1%
#2256
0%
#2258
b1000110101 8
1%
#2260
0%
#2262
b1000110110 8
1%
#2264
0%
#2266
b1000110111 8
1%
#2268
0%
#2270
b1000111000 8
1%
#2272
0%
#2274
b1000111001 8
1%
#2276
0%
#2278
b1000111010 8
1%
#2280
0%
#2282
b1000111011 8
1%
#2284
0%
#2286
b1000111100 8
1%
#2288
0%
#2290
b1000111101 8
1%
#2292
0%
#2294
b1000111110 8
1%
#2296
0%
#2298
b1000111111 8
1%
#2300
0%
#2302
b1001000000 8
1%
#2304
0%
#2306
b1001000001 8
1%
#2308
0%
#2310
b1001000010 8
1%
#2312
0%
#2314
b1001000011 8
1%
#2316
0%
#2318
b1001000100 8
1%
#2320
0%
#2322
b1001000101 8
1%
#2324
0%
#2326
b1001000110 8
1%
#2328
0%
#2330
b1001000111 8
1%
#2332
0%
#2334
b1001001000 8
1%
#2336
0%
#2338
b1001001001 8
1%
#2340
0%
#2342
b1001001010 8
1%
#2344
0%
#2346
b1001001011 8
1%
#2348
0%
#2350
b1001001100 8
1%
#2352
0%
#2354
b1001001101 8
1%
#2356
0%
